INP_Calc/__init__.py
INP_Calc/calculations.py
inp_calc-0.2.7.dist-info/METADATA
inp_calc-0.2.7.dist-info/WHEEL
inp_calc-0.2.7.dist-info/top_level.txt
inp_calc-0.2.7.dist-info/RECORD
