Metadata-Version: 2.2
Name: INP_Calc
Version: 0.2.7
Summary: Functions for converting frozen fraction (FF) to concentration, volume, and surface area.
Author: Max Fobian Skov
Author-email: max.fobian@gmail.com
License: MIT
Requires-Python: >=3.9
Requires-Dist: numpy>=1.21.0
Requires-Dist: pandas>=1.3.0
Requires-Dist: scipy>=1.7.0
Requires-Dist: matplotlib>=3.10.1
Dynamic: author
Dynamic: author-email
Dynamic: description
Dynamic: description-content-type
Dynamic: license
Dynamic: requires-dist
Dynamic: requires-python
Dynamic: summary
